ruthie/__init__.py
ruthie/__main__.py
ruthie/cli.py
ruthie/commands/__init__.py
ruthie/commands/base.py
ruthie/commands/discover.py
ruthie/commands/parallel.py
ruthie/toolset/__init__.py
ruthie/toolset/discoverer.py
ruthie-0.1.5.dist-info/LICENSE
ruthie-0.1.5.dist-info/METADATA
ruthie-0.1.5.dist-info/WHEEL
ruthie-0.1.5.dist-info/top_level.txt
ruthie-0.1.5.dist-info/RECORD
