Metadata-Version: 2.1
Name: ruthie
Version: 0.1.5
License-File: LICENSE
